giusas
