Metadata-Version: 1.0
Name: giusas
Version: 2017.4.29
Summary: GISAXS and GIWAXS calculator
Home-page: https://hg.3lp.cx/giusas
Author: Vadim Dyadkin
Author-email: dyadkin@gmail.com
License: GPLv3
Platform: UNKNOWN
